Workbook

Sheet Assumptions
B2: Assumptions
B4: Parameter | C4: Assumed value | D4: Unit | E4: Comments
B5: INVESTMENT
B6: Initial investment | C6: 100000 | D6: € | E6: One-time cost in Year 0
B7: System lifetime | C7: 10 | D7: years | E7: Analysis horizon
B8: Residual value | C8: 15000 | D8: € | E8: Estimated value at end of Year 10
B9: ANNUAL COSTS
B10: Maintenance cost | C10: 3000 | D10: €/year | E10: Annual servicing
B11: ANNUAL BENEFITS
B12: Energy cost savings | C12: 30000 | D12: €/year | E12: Reduced electricity we have to buy from the market
B13: Avoided carbon tax | C13: 2000 | D13: €/year | E13: Estimated regulatory saving
B14: DISCOUNT RATE
B15: Discount rate | C15: 0.05 | D15: % | E15: Cost of capital / required return

Sheet CBA
B2: CBA - 10 year Cash Flow Model
C4: 0 | D4: 1 | E4: 2 | F4: 3 | G4: 4 | H4: 5 | I4: 6 | J4: 7 | K4: 8 | L4: 9 | M4: 10
B5: Positions | C5: ="Year " &C4 -> Year 0 | D5: ="Year " &D4 -> Year 1 | E5: ="Year " &E4 -> Year 2 | F5: ="Year " &F4 -> Year 3 | G5: ="Year " &G4 -> Year 4 | H5: ="Year " &H4 -> Year 5 | I5: ="Year " &I4 -> Year 6 | J5: ="Year " &J4 -> Year 7 | ... M5: ="Year " &M4 -> Year 10
B6: COSTS
B7: Initial Investment (€) | C7: =Assumptions!$C$6 -> 100000
B8: Annual Maintenance Cost (€) | D8: =Assumptions!$C$10 -> 3000 | E8: =Assumptions!$C$10 -> 3000 | F8: =Assumptions!$C$10 -> 3000 | G8: =Assumptions!$C$10 -> 3000 | H8: =Assumptions!$C$10 -> 3000 | I8: =Assumptions!$C$10 -> 3000 | J8: =Assumptions!$C$10 -> 3000 | K8: =Assumptions!$C$10 -> 3000 | ... M8: =Assumptions!$C$10 -> 3000
B9: TOTAL COSTS (€) | C9: =SUM(C7:C8) -> 100000 | D9: =SUM(D7:D8) -> 3000 | E9: =SUM(E7:E8) -> 3000 | F9: =SUM(F7:F8) -> 3000 | G9: =SUM(G7:G8) -> 3000 | H9: =SUM(H7:H8) -> 3000 | I9: =SUM(I7:I8) -> 3000 | J9: =SUM(J7:J8) -> 3000 | ... M9: =SUM(M7:M8) -> 3000
B10: BENEFITS
B11: Energy Cost Savings (€) | D11: =Assumptions!$C$12 -> 30000 | E11: =Assumptions!$C$12 -> 30000 | F11: =Assumptions!$C$12 -> 30000 | G11: =Assumptions!$C$12 -> 30000 | H11: =Assumptions!$C$12 -> 30000 | I11: =Assumptions!$C$12 -> 30000 | J11: =Assumptions!$C$12 -> 30000 | K11: =Assumptions!$C$12 -> 30000 | ... M11: =Assumptions!$C$12 -> 30000
B12: Avoided Carbon Tax (€) | D12: =Assumptions!$C$13 -> 2000 | E12: =Assumptions!$C$13 -> 2000 | F12: =Assumptions!$C$13 -> 2000 | G12: =Assumptions!$C$13 -> 2000 | H12: =Assumptions!$C$13 -> 2000 | I12: =Assumptions!$C$13 -> 2000 | J12: =Assumptions!$C$13 -> 2000 | K12: =Assumptions!$C$13 -> 2000 | ... M12: =Assumptions!$C$13 -> 2000
B13: Residual Value (€) | M13: =Assumptions!$C$8 -> 15000
B14: TOTAL BENEFITS (€) | C14: =SUM(C11:C13) -> 0 | D14: =SUM(D11:D13) -> 32000 | E14: =SUM(E11:E13) -> 32000 | F14: =SUM(F11:F13) -> 32000 | G14: =SUM(G11:G13) -> 32000 | H14: =SUM(H11:H13) -> 32000 | I14: =SUM(I11:I13) -> 32000 | J14: =SUM(J11:J13) -> 32000 | ... M14: =SUM(M11:M13) -> 47000
B15: NET CASH FLOW & DISCOUNTING
B16: Net Cash Flow (€) | C16: =C14-C9 -> -100000 | D16: =D14-D9 -> 29000 | E16: =E14-E9 -> 29000 | F16: =F14-F9 -> 29000 | G16: =G14-G9 -> 29000 | H16: =H14-H9 -> 29000 | I16: =I14-I9 -> 29000 | J16: =J14-J9 -> 29000 | ... M16: =M14-M9 -> 44000
B17: Discount Factor | C17: 1 | D17: =1/(1+Assumptions!$C$15)^D4 -> 0.95238095 | E17: =1/(1+Assumptions!$C$15)^E4 -> 0.90702948 | F17: =1/(1+Assumptions!$C$15)^F4 -> 0.8638376 | G17: =1/(1+Assumptions!$C$15)^G4 -> 0.82270247 | H17: =1/(1+Assumptions!$C$15)^H4 -> 0.78352617 | I17: =1/(1+Assumptions!$C$15)^I4 -> 0.7462154 | J17: =1/(1+Assumptions!$C$15)^J4 -> 0.71068133 | K17: =1/(1+Assumptions!$C$15)^K4 -> 0.67683936 | ... M17: =1/(1+Assumptions!$C$15)^M4 -> 0.61391325
B18: Present Value of Cash Flow (€) | C18: =C16*C17 -> -100000 | D18: =D16*D17 -> 27619.048 | E18: =E16*E17 -> 26303.855 | F18: =F16*F17 -> 25051.29 | G18: =G16*G17 -> 23858.372 | H18: =H16*H17 -> 22722.259 | I18: =I16*I17 -> 21640.247 | J18: =J16*J17 -> 20609.759 | ... M18: =M16*M17 -> 27012.183
B19: Cumulative Net Present Value - NPV (€) | C19: =C18 -> -100000 | D19: =C19+D18 -> -72380.952 | E19: =D19+E18 -> -46077.098 | F19: =E19+F18 -> -21025.807 | G19: =F19+G18 -> 2832.5646 | H19: =G19+H18 -> 25554.823 | I19: =H19+I18 -> 47195.07 | J19: =I19+J18 -> 67804.829 | K19: =J19+K18 -> 87433.17 | ... M19: =L19+M18 -> 133139.01
B22: Benefits & Costs Overview
B24: Total Undiscounted Costs (€) | C24: =SUM(C9:M9) -> 130000
B25: Total Undiscounted Benefits (€) | C25: =SUM(C14:M14) -> 335000
B26: Net Present Value - NPV (€) | C26: =M19 -> 133139.01
B27: Benefit-Cost Ratio - BCR [-] | C27: =C25/C24 -> 2.5769231
B28: Payback Period (approx. years) | C28: 7

Sheet Sensitivity Analysis
B2: How robust is our result?
B4: Scenario | C4: Changed Assumption | D4: Value | E4: Unit | F4: NPV [€] | G4: BCR [-] | H4: Payback period [y]
B5: Base Case | C5: - | D5: - | E5: - | F5: 55921.662 | G5: 1.81 | H5: 7
B6: Higher energy prices | C6: Energy savings +50% | D6: =Assumptions!C12*1.5 -> 45000 | E6: €/year | F6: 133139.01 | G6: 2.58 | H6: 4
B7: Lower energy prices | C7: Energy savings -50% | D7: =Assumptions!C12*0.5 -> 15000 | E7: €/year
B8: Higher discount rate | C8: Discount rate 8% | D8: 0.08 | E8: %
B9: Lower discount rate | C9: Discount rate 3% | D9: 0.03 | E9: %
B10: Avoided carbon tax | C10: CO₂ revenue = €0 | D10: 1000 | E10: €/year

Sheet ###

Sheet complete Assumptions
B2: Assumptions
B4: Parameter | C4: Assumed value | D4: Unit | E4: Comments
B5: INVESTMENT
B6: Initial investment | C6: 100000 | D6: € | E6: One-time cost in Year 0
B7: System lifetime | C7: 10 | D7: years | E7: Analysis horizon
B8: Residual value | C8: 15000 | D8: € | E8: Estimated value at end of Year 10
B9: ANNUAL COSTS
B10: Maintenance cost | C10: 3000 | D10: €/year | E10: Annual servicing
B11: ANNUAL BENEFITS
B12: Energy cost savings | C12: 20000 | D12: €/year | E12: Reduced electricity we have to buy from the market
B13: Avoided carbon tax | C13: 2000 | D13: €/year | E13: Estimated regulatory saving
B14: DISCOUNT RATE
B15: Discount rate | C15: 0.05 | D15: % | E15: Cost of capital / required return

Sheet complete CBA
B2: CBA - 10 year Cash Flow Model
C4: 0 | D4: 1 | E4: 2 | F4: 3 | G4: 4 | H4: 5 | I4: 6 | J4: 7 | K4: 8 | L4: 9 | M4: 10
B5: Positions | C5: ="Year " &C4 -> Year 0 | D5: ="Year " &D4 -> Year 1 | E5: ="Year " &E4 -> Year 2 | F5: ="Year " &F4 -> Year 3 | G5: ="Year " &G4 -> Year 4 | H5: ="Year " &H4 -> Year 5 | I5: ="Year " &I4 -> Year 6 | J5: ="Year " &J4 -> Year 7 | ... M5: ="Year " &M4 -> Year 10
B6: COSTS
B7: Initial Investment (€) | C7: =-'complete Assumptions'!C6 -> -100000
B8: Annual Maintenance Cost (€) | D8: =-'complete Assumptions'!$C$10 -> -3000 | E8: =-'complete Assumptions'!$C$10 -> -3000 | F8: =-'complete Assumptions'!$C$10 -> -3000 | G8: =-'complete Assumptions'!$C$10 -> -3000 | H8: =-'complete Assumptions'!$C$10 -> -3000 | I8: =-'complete Assumptions'!$C$10 -> -3000 | J8: =-'complete Assumptions'!$C$10 -> -3000 | K8: =-'complete Assumptions'!$C$10 -> -3000 | ... M8: =-'complete Assumptions'!$C$10 -> -3000
B9: TOTAL COSTS (€) | C9: =SUM(C7:C8) -> -100000 | D9: =SUM(D7:D8) -> -3000 | E9: =SUM(E7:E8) -> -3000 | F9: =SUM(F7:F8) -> -3000 | G9: =SUM(G7:G8) -> -3000 | H9: =SUM(H7:H8) -> -3000 | I9: =SUM(I7:I8) -> -3000 | J9: =SUM(J7:J8) -> -3000 | ... M9: =SUM(M7:M8) -> -3000
B10: BENEFITS
B11: Energy Cost Savings (€) | D11: ='complete Assumptions'!$C$12 -> 20000 | E11: ='complete Assumptions'!$C$12 -> 20000 | F11: ='complete Assumptions'!$C$12 -> 20000 | G11: ='complete Assumptions'!$C$12 -> 20000 | H11: ='complete Assumptions'!$C$12 -> 20000 | I11: ='complete Assumptions'!$C$12 -> 20000 | J11: ='complete Assumptions'!$C$12 -> 20000 | K11: ='complete Assumptions'!$C$12 -> 20000 | ... M11: ='complete Assumptions'!$C$12 -> 20000
B12: Avoided Carbon Tax (€) | D12: ='complete Assumptions'!$C$13 -> 2000 | E12: ='complete Assumptions'!$C$13 -> 2000 | F12: ='complete Assumptions'!$C$13 -> 2000 | G12: ='complete Assumptions'!$C$13 -> 2000 | H12: ='complete Assumptions'!$C$13 -> 2000 | I12: ='complete Assumptions'!$C$13 -> 2000 | J12: ='complete Assumptions'!$C$13 -> 2000 | K12: ='complete Assumptions'!$C$13 -> 2000 | ... M12: ='complete Assumptions'!$C$13 -> 2000
B13: Residual Value (€) | M13: ='complete Assumptions'!$C$8 -> 15000
B14: TOTAL BENEFITS (€) | C14: =SUM(C10:C13) -> 0 | D14: =SUM(D10:D13) -> 22000 | E14: =SUM(E10:E13) -> 22000 | F14: =SUM(F10:F13) -> 22000 | G14: =SUM(G10:G13) -> 22000 | H14: =SUM(H10:H13) -> 22000 | I14: =SUM(I10:I13) -> 22000 | J14: =SUM(J10:J13) -> 22000 | ... M14: =SUM(M10:M13) -> 37000
B15: NET CASH FLOW & DISCOUNTING
B16: Net Cash Flow (€) | C16: =C14+C9 -> -100000 | D16: =D14+D9 -> 19000 | E16: =E14+E9 -> 19000 | F16: =F14+F9 -> 19000 | G16: =G14+G9 -> 19000 | H16: =H14+H9 -> 19000 | I16: =I14+I9 -> 19000 | J16: =J14+J9 -> 19000 | ... M16: =M14+M9 -> 34000
B17: Discount Factor | C17: 1 | D17: =1/(1+'complete Assumptions'!$C$15)^D4 -> 0.95238095 | E17: =1/(1+'complete Assumptions'!$C$15)^E4 -> 0.90702948 | F17: =1/(1+'complete Assumptions'!$C$15)^F4 -> 0.8638376 | G17: =1/(1+'complete Assumptions'!$C$15)^G4 -> 0.82270247 | H17: =1/(1+'complete Assumptions'!$C$15)^H4 -> 0.78352617 | I17: =1/(1+'complete Assumptions'!$C$15)^I4 -> 0.7462154 | J17: =1/(1+'complete Assumptions'!$C$15)^J4 -> 0.71068133 | K17: =1/(1+'complete Assumptions'!$C$15)^K4 -> 0.67683936 | ... M17: =1/(1+'complete Assumptions'!$C$15)^M4 -> 0.61391325
B18: Present Value of Cash Flow (€) | C18: =C16*C17 -> -100000 | D18: =D16*D17 -> 18095.238 | E18: =E16*E17 -> 17233.56 | F18: =F16*F17 -> 16412.914 | G18: =G16*G17 -> 15631.347 | H18: =H16*H17 -> 14886.997 | I18: =I16*I17 -> 14178.093 | J18: =J16*J17 -> 13502.945 | ... M18: =M16*M17 -> 20873.051
B19: Cumulative Net Present Value - NPV (€) | C19: =C18 -> -100000 | D19: =C19+D18 -> -81904.762 | E19: =D19+E18 -> -64671.202 | F19: =E19+F18 -> -48258.287 | G19: =F19+G18 -> -32626.94 | H19: =G19+H18 -> -17739.943 | I19: =H19+I18 -> -3561.8507 | J19: =I19+J18 -> 9941.0946 | K19: =J19+K18 -> 22801.042 | ... M19: =L19+M18 -> 55921.662
B22: Benefits & Costs Overview
B24: Total Undiscounted Costs (€) | C24: =SUM(C9:M9) -> -130000
B25: Total Undiscounted Benefits (€) | C25: =SUM(C14:M14) -> 235000
B26: Net Present Value - NPV (€) | C26: =M19 -> 55921.662
B27: Benefit-Cost Ratio - BCR [-] | C27: =-1*(C25/C24) -> 1.8076923
B28: Payback Period (approx. years) | C28: 7

Sheet complete Sensitivity Analysis
B2: How robust is our result?
B4: Scenario | C4: Changed Assumption | D4: Value | E4: Unit | F4: NPV [€] | G4: BCR [-] | H4: Payback period [y]
B5: Base Case | C5: - | D5: - | E5: - | F5: 55921.662 | G5: 1.8076923 | H5: 7
B6: Higher energy prices | C6: Energy savings +50% | D6: ='complete Assumptions'!C12*1.5 -> 30000 | E6: €/year
B7: Lower energy prices | C7: Energy savings -50% | D7: ='complete Assumptions'!C12*0.5 -> 10000 | E7: €/year
B8: Higher discount rate | C8: Discount rate 8% | D8: 0.08 | E8: %
B9: Lower discount rate | C9: Discount rate 3% | D9: 0.03 | E9: %
B10: Avoided carbon tax | C10: CO₂ revenue = €0 | D10: 1000 | E10: €/year
